{
    "song_zelda": {
        "notes": ["L","U","R","L","U","R"],
        "editable": true
    },
    "song_saria": {
        "notes": ["D","R","L","D","R","L"],
        "editable": true
    },
    "song_epona": {
        "notes": ["U","L","R","U","L","R"],
        "editable": true
    },
    "song_sun": {
        "notes": ["R","D","U","R","D","U"],
        "editable": true
    },
    "song_time": {
        "notes": ["R","A","D","R","A","D"],
        "editable": true
    },
    "song_storm": {
        "notes": ["A","D","U","A","D","U"],
        "editable": true
    },
    "warp_forest": {
        "notes": ["A","U","L","R","L","R"],
        "editable": true
    },
    "warp_fire": {
        "notes": ["D","A","D","A","R","D","R","D"],
        "editable": true
    },
    "warp_water": {
        "notes": ["A","D","R","R","L"],
        "editable": true
    },
    "warp_shadow": {
        "notes": ["L","R","R","A","L","R","D"],
        "editable": true
    },
    "warp_spirit": {
        "notes": ["A","D","A","R","D","A"],
        "editable": true
    },
    "warp_light": {
        "notes": ["U","R","U","R","L","U"],
        "editable": true
    },
    "song_scarecrow": {
        "notes": [],
        "editable": true
    },
    "song_frogs": {
        "notes": ["A","L","R","D","L","R","D","A","D","A","D","R","L","A"],
        "editable": false
    },
    "song_woods": {
        "notes": [],
        "editable": true
    }
}